{
  "books-plans": [
    { "id": 1, "title": "Столпы Земли", "author": "Фоллет" },
    { "id": 2, "title": "Доктор Живаго", "author": "Борис Пастернак" },
    { "id": 3, "title": "Обитель", "author": "Захар Прилепин" },
    { "id": 4, "title": "Американские боги", "author": "Нил Гейман" }
  ],
  "books-done": [
    { "id": 1, "title": "Июнь", "author": "Дмитрий быков" },
    { "id": 2, "title": "Солярис", "author": "Станислав Лем" },
    { "id": 3, "title": "Город еритиков", "author": "Федерико Андахази" },
    { "id": 4, "title": "Машина времени", "author": "Герберт Велс" }
  ]
}
